setup.py
django_pariah.egg-info/PKG-INFO
django_pariah.egg-info/SOURCES.txt
django_pariah.egg-info/dependency_links.txt
django_pariah.egg-info/requires.txt
django_pariah.egg-info/top_level.txt
pariah/__init__.py
pariah/admin.py
pariah/models.py
pariah/urls.py
pariah/views.py