Metadata-Version: 1.0
Name: django-pariah
Version: 0.2
Summary: A Django app for creating web comics
Home-page: https://github.com/rockstar/django-pariah
Author: Paul Hummer @ Amelia, LLC
Author-email: paul@ameliaknows.com
License: http://www.opensource.org/licenses/mit-license.php
Keywords: django comics webcomics
Platform: UNKNOWN
